djhx_bilix/__init__.py
djhx_bilix/__main__.py
djhx_bilix/cli.py
djhx_bilix/ffmpeg.exe
djhx_bilix/global_param.py
djhx_bilix/tool.py
djhx_bilix/account/__init__.py
djhx_bilix/config/__init__.py
djhx_bilix/config/app_config.py
djhx_bilix/config/log_config.py
djhx_bilix/video/__init__.py
djhx_bilix/video/video_info.py
djhx_bilix-1.3.2.dist-info/licenses/LICENSE
djhx_bilix-1.3.2.dist-info/METADATA
djhx_bilix-1.3.2.dist-info/WHEEL
djhx_bilix-1.3.2.dist-info/entry_points.txt
djhx_bilix-1.3.2.dist-info/top_level.txt
djhx_bilix-1.3.2.dist-info/RECORD
