Metadata-Version: 2.4
Name: djhx-bilix
Version: 1.3.2
Summary: A simple Bilibili video download tool, support user login.
Requires-Python: >=3.14
License-File: LICENSE
Requires-Dist: curl-cffi>=0.13.0
Requires-Dist: nuitka>=2.8.9
Requires-Dist: platformdirs>=4.5.1
Requires-Dist: pypng>=0.20220715.0
Requires-Dist: qrcode>=8.2
Requires-Dist: requests>=2.32.5
Requires-Dist: typer>=0.20.0
Dynamic: license-file
